attrLinker/__init__.py
attrLinker/attrLinker.py
attrLinker/decorator.py
attrLinker/exceptions.py
attrLinker/linkMethod.py
attrLinker/preparedLink.py
attrLinker/presets.py
attrLinker/propBinder.py
attrLinker/utils.py
AttrLinker-0.0.6.dist-info/LICENSE
AttrLinker-0.0.6.dist-info/METADATA
AttrLinker-0.0.6.dist-info/WHEEL
AttrLinker-0.0.6.dist-info/top_level.txt
AttrLinker-0.0.6.dist-info/RECORD
