Metadata-Version: 2.1
Name: AttrLinker
Version: 0.0.6
Summary: A package for assisting linking attributes.
Home-page: https://github.com/Vin-Ren/AttrLinker
Author: Vin-Ren
Author-email: reaxumrx@gmail.com
License: UNKNOWN
Project-URL: Bug Tracker, https://github.com/Vin-Ren/AttrLinker/issues
Platform: UNKNOWN
Classifier: Programming Language :: Python :: 3
Classifier: License :: OSI Approved :: MIT License
Classifier: Operating System :: OS Independent
Requires-Python: >=3.6
License-File: LICENSE
